{
  "name": "TypeScript Development",
  "build": {
    "dockerfile": "Dockerfile",
    "context": "."
  },
  "appPort": [
    3000
  ],
  "containerEnv": {
    "SSH_CONTEXT": "default",
    "ZSH_PROFILE": "devcontainer",
    "AWS_PAGER": "",
    "HOME": "/home/node",
    "USER": "node",
    "WORKSPACE_ROOT": "${containerWorkspaceFolder}",
    "TMUX_SESSION": "vsc-${containerWorkspaceFolderBasename}",
    "GITHUB_USERNAME": "",
    "GIT_NAME": "",
    "GIT_EMAIL": ""
  },
  "customizations": {
    "vscode": {
      "extensions": [
        "ms-vscode.vscode-typescript-next",
        "usernamehw.errorlens",
        "streetsidesoftware.code-spell-checker",
        "eetami.whitespace-formatter",
        "redhat.vscode-yaml",
        "esbenp.prettier-vscode",
        "bradlc.vscode-tailwindcss",
        "amazonwebservices.aws-toolkit-vscode",
        "amazonwebservices.amazon-q-vscode",
        "dbaeumer.vscode-eslint",
        "GitHub.copilot-chat"
      ],
      "settings": {
        "terminal.integrated.defaultProfile.linux": "tmux",
        "editor.defaultFormatter": "esbenp.prettier-vscode",
        "editor.formatOnSave": true,
        "editor.formatOnType": false,
        "editor.formatOnPaste": true,
        "editor.formatOnSaveMode": "file",
        "files.autoSave": "onFocusChange",
        "typescript.preferences.importModuleSpecifier": "relative",
        "editor.codeActionsOnSave": {
          "source.formatDocument": true,
          "source.fixAll.eslint": true,
          "source.organizeImports": true
        },
        "[typescript][typescriptreact]": {
          "editor.defaultFormatter": "esbenp.prettier-vscode"
        },
        "[json][jsonc]": {
          "editor.defaultFormatter": "esbenp.prettier-vscode"
        }
      }
    }
  },
  "mounts": [],
  "postCreateCommand": "/bin/sh /usr/src/post_create.sh",
  "remoteUser": "node"
}